earcp/__init__.py
earcp/config.py
earcp/core/__init__.py
earcp/core/coherence_metrics.py
earcp/core/ensemble_weighting.py
earcp/core/performance_tracker.py
earcp/models/__init__.py
earcp/models/earcp_model.py
earcp/utils/__init__.py
earcp/utils/metrics.py
earcp/utils/visualization.py
earcp/utils/wrappers.py
earcp-1.0.0.dist-info/METADATA
earcp-1.0.0.dist-info/WHEEL
earcp-1.0.0.dist-info/top_level.txt
earcp-1.0.0.dist-info/RECORD
