Metadata-Version: 2.4
Name: earcp
Version: 1.0.0
Summary: EARCP: Self-Regulating Coherence and Performance-Aware Ensemble
Home-page: https://github.com/Volgat/earcp
Author: Mike Amega
Author-email: info@amewebstudio.com
License: Business Source License 1.1
Project-URL: Documentation, https://github.com/Volgat/earcp/blob/main/docs/USAGE.md
Project-URL: Source, https://github.com/Volgat/earcp/tree/earcp-lib
Project-URL: Bug Reports, https://github.com/Volgat/earcp/issues
Project-URL: License, https://github.com/Volgat/earcp/blob/main/LICENSE.md
Project-URL: Commercial Licensing, https://github.com/Volgat/earcp/blob/earcp-lib/LICENSE
Keywords: machine-learning,ensemble-learning,online-learning,adaptive-algorithms,model-combination,expert-weighting,coherence,performance,sequential-decision-making,dynamic-weighting,trading,forecasting
Classifier: Development Status :: 4 - Beta
Classifier: Intended Audience :: Science/Research
Classifier: Intended Audience :: Developers
Classifier: Intended Audience :: Financial and Insurance Industry
Classifier: Topic :: Scientific/Engineering :: Artificial Intelligence
Classifier: Topic :: Scientific/Engineering :: Information Analysis
Classifier: Topic :: Software Development :: Libraries :: Python Modules
Classifier: License :: Other/Proprietary License
Classifier: Programming Language :: Python :: 3
Classifier: Programming Language :: Python :: 3.8
Classifier: Programming Language :: Python :: 3.9
Classifier: Programming Language :: Python :: 3.10
Classifier: Programming Language :: Python :: 3.11
Classifier: Programming Language :: Python :: 3.12
Classifier: Operating System :: OS Independent
Classifier: Natural Language :: English
Requires-Python: >=3.8
Requires-Dist: numpy>=1.20.0
Requires-Dist: scipy>=1.7.0
Requires-Dist: matplotlib>=3.3.0
Provides-Extra: dev
Requires-Dist: pytest>=6.0; extra == "dev"
Requires-Dist: pytest-cov>=2.0; extra == "dev"
Requires-Dist: black>=21.0; extra == "dev"
Requires-Dist: flake8>=3.9; extra == "dev"
Requires-Dist: mypy>=0.910; extra == "dev"
Provides-Extra: torch
Requires-Dist: torch>=1.9.0; extra == "torch"
Provides-Extra: sklearn
Requires-Dist: scikit-learn>=0.24.0; extra == "sklearn"
Provides-Extra: full
Requires-Dist: torch>=1.9.0; extra == "full"
Requires-Dist: scikit-learn>=0.24.0; extra == "full"
Requires-Dist: pandas>=1.3.0; extra == "full"
Requires-Dist: seaborn>=0.11.0; extra == "full"
Dynamic: author
Dynamic: author-email
Dynamic: classifier
Dynamic: description
Dynamic: description-content-type
Dynamic: home-page
Dynamic: keywords
Dynamic: license
Dynamic: project-url
Dynamic: provides-extra
Dynamic: requires-dist
Dynamic: requires-python
Dynamic: summary
